fpfind/__init__.py
fpfind/_postinstall
fpfind/apps/fpplot.py
fpfind/apps/g2_two_timestamps.py
fpfind/apps/generate_freqcd_testcase.py
fpfind/apps/generate_freqdetuneg2.py
fpfind/apps/show-timestamps
fpfind/apps/show-timestamps-hex
fpfind/apps/tsviz.py
fpfind/fpfind.py
fpfind/freqcd
fpfind/freqcd.c
fpfind/freqservo.py
fpfind/lib/constants.py
fpfind/lib/getopt.c
fpfind/lib/getopt.h
fpfind/lib/logging.py
fpfind/lib/parse_epochs.py
fpfind/lib/parse_timestamps.py
fpfind/lib/typing.py
fpfind/lib/utils.py
fpfind-3.3.4.data/scripts/freqcd
fpfind-3.3.4.data/scripts/show-timestamps
fpfind-3.3.4.data/scripts/show-timestamps-hex
fpfind-3.3.4.dist-info/METADATA
fpfind-3.3.4.dist-info/WHEEL
fpfind-3.3.4.dist-info/entry_points.txt
fpfind-3.3.4.dist-info/licenses/LICENSE
fpfind-3.3.4.dist-info/RECORD
