Metadata-Version: 2.4
Name: fpfind
Version: 3.3.4
Summary: Add-on implementation of frequency compensation for qcrypto.
License: GPLv2
License-File: LICENSE
Keywords: qkd,qcrypto,clock-synchronization,frequency-correction
Author: Xu Zifang
Author-email: francium0415@gmail.com
Maintainer: S-Fifteen Instruments
Maintainer-email: info@s-fifteen.com
Requires-Python: >=3.8
Classifier: Development Status :: 5 - Production/Stable
Classifier: Intended Audience :: Developers
Classifier: Intended Audience :: Science/Research
Classifier: License :: OSI Approved :: GNU General Public License v2 (GPLv2)
Classifier: License :: Other/Proprietary License
Classifier: Natural Language :: English
Classifier: Operating System :: POSIX :: Linux
Classifier: Programming Language :: Python :: 3
Classifier: Programming Language :: Python :: 3.8
Classifier: Programming Language :: Python :: 3.9
Classifier: Programming Language :: Python :: 3.10
Classifier: Programming Language :: Python :: 3.11
Classifier: Programming Language :: Python :: 3.12
Classifier: Programming Language :: Python :: 3.13
Classifier: Programming Language :: Python :: 3.14
Classifier: Topic :: Scientific/Engineering :: Physics
Requires-Dist: configargparse (>=1.7)
Requires-Dist: matplotlib (>=3.6.3)
Requires-Dist: numba (>=0.57.0)
Requires-Dist: numpy (>=1.24.4)
Requires-Dist: scipy (>=1.10.0) ; python_version >= "3.9"
Requires-Dist: scipy (>=1.10.0,<1.11) ; python_version == "3.8"
Requires-Dist: tqdm (>=4.65.0)
Requires-Dist: typing_extensions (>=4.13.2)
